<annotation verified="yes"><folder>images\qmul_toplogo10\jpg\chanel</folder><filename>chanel67.jpg</filename><path>C:\Users\Kyle\Desktop\college\Senior_Project\Priatek-CV\Object-Detection\images\qmul_toplogo10\jpg\chanel\chanel67.jpg</path><source><database>Unknown</database></source><size><width>368</width><height>398</height><depth>3</depth></size><segmented>0</segmented><object><name>chanel</name><pose>Unspecified</pose><truncated>0</truncated><difficult>0</difficult><bndbox><xmin>148</xmin><ymin>160</ymin><xmax>344</xmax><ymax>288</ymax></bndbox></object></annotation>