<annotation verified="yes"><folder>images\qmul_toplogo10\jpg\adidas</folder><filename>adidas18.jpg</filename><path>C:\Users\Kyle\Desktop\college\Senior_Project\Priatek-CV\Object-Detection\images\qmul_toplogo10\jpg\adidas\adidas18.jpg</path><source><database>Unknown</database></source><size><width>338</width><height>220</height><depth>3</depth></size><segmented>0</segmented><object><name>adidas</name><pose>Unspecified</pose><truncated>0</truncated><difficult>0</difficult><bndbox><xmin>88</xmin><ymin>28</ymin><xmax>120</xmax><ymax>50</ymax></bndbox></object></annotation>